.DS_Store
plotvet/__init__.py
plotvet/plotvet.py
plotvet-0.0.11.dist-info/LICENSE
plotvet-0.0.11.dist-info/METADATA
plotvet-0.0.11.dist-info/WHEEL
plotvet-0.0.11.dist-info/top_level.txt
plotvet-0.0.11.dist-info/RECORD
