Metadata-Version: 2.1
Name: plotvet
Version: 0.0.11
Summary: Pacote python para plotagem de vetores em planos bidimensionais e espaços tridimensionais
Home-page: https://github.com/marcos-de-sousa/plotvet
Author: Marcos Paulo Alves de Sousa
Author-email: desousa.mpa@gmail.com
License: MIT License
Keywords: Pacote
Platform: UNKNOWN
Requires-Dist: numpy
Requires-Dist: matplotlib
